{
    "format_version": "1.20.0",
    "minecraft:recipe_shaped": {
        "description": {
            "identifier": "skyblock:compressed_tuff_from_tuff"
        },
        "tags": [
            "crafting_table"
        ],
        "pattern": [
            "AAA",
            "AAA",
            "AAA"
        ],
        "key": {
            "A": {
                "item": "minecraft:tuff"
            }
        },
        "result": {
            "item": "skyblock:compressed_tuff",
            "count": 1
        }
    }
}