{
    "format_version": "1.20.0",
    "minecraft:recipe_shaped": {
        "description": {
            "identifier": "skyblock:septuple_compressed_emerald_block_from_sextuple_compressed_emerald_block"
        },
        "tags": [
            "crafting_table"
        ],
        "pattern": [
            "AAA",
            "AAA",
            "AAA"
        ],
        "key": {
            "A": {
                "item": "skyblock:sextuple_compressed_emerald_block"
            }
        },
        "result": {
            "item": "skyblock:septuple_compressed_emerald_block",
            "count": 1
        }
    }
}